LICENSE
MANIFEST.in
README.rst
setup.cfg
setup.py
kylinpy/__init__.py
kylinpy/cli.py
kylinpy/exceptions.py
kylinpy/kylindb.py
kylinpy/kylinpy.py
kylinpy/logger.py
kylinpy/sqla_dialect.py
kylinpy/client/__init__.py
kylinpy/client/client.py
kylinpy/client/exceptions.py
kylinpy/datasource/__init__.py
kylinpy/datasource/_source_interface.py
kylinpy/datasource/cube_source.py
kylinpy/datasource/hive_source.py
kylinpy/utils/__init__.py
kylinpy/utils/compat.py
kylinpy/utils/keywords.py
kylinpy/utils/kylin_types.py
kylinpy/utils/sqla_types.py
kylinpy_dm.egg-info/PKG-INFO
kylinpy_dm.egg-info/SOURCES.txt
kylinpy_dm.egg-info/dependency_links.txt
kylinpy_dm.egg-info/entry_points.txt
kylinpy_dm.egg-info/requires.txt
kylinpy_dm.egg-info/top_level.txt
tests/__init__.py
tests/test_client.py
tests/test_dialect.py